apigen/__init__.py
apigen/apigen.py
apigen/version.py
apigen-1.5.0.dist-info/DESCRIPTION.rst
apigen-1.5.0.dist-info/METADATA
apigen-1.5.0.dist-info/RECORD
apigen-1.5.0.dist-info/WHEEL
apigen-1.5.0.dist-info/metadata.json
apigen-1.5.0.dist-info/top_level.txt
