Metadata-Version: 2.0
Name: apigen
Version: 1.5.0
Summary: Easily create a CLI and JSON-RPC interface from a common API definition.
Home-page: https://github.com/F483/apigen/
Author: Fabian Barkhau
Author-email: fabian.barkhau@gmail.com
License: MIT
Keywords: CLI,JSON,RPC,JSON-RPC,API,Remote Procedure Call,JavaScript Object Notation,argparse,Data Interchange
Platform: UNKNOWN
Classifier: Development Status :: 5 - Production/Stable
Classifier: Intended Audience :: Developers
Classifier: License :: OSI Approved :: MIT License
Classifier: Operating System :: OS Independent
Classifier: Programming Language :: Python
Classifier: Programming Language :: Python :: 2
Classifier: Programming Language :: Python :: 2.7
Classifier: Topic :: Software Development :: Libraries :: Python Modules
Requires-Dist: argparse (==1.2.1)
Requires-Dist: python-jsonrpc (==0.7.8)
